README.md
setup.py
pytry/__init__.py
pytry/cmdline.py
pytry/many.py
pytry/nengo.py
pytry/parser.py
pytry/plot.py
pytry/read.py
pytry/trial.py
pytry/write.py
pytry.egg-info/PKG-INFO
pytry.egg-info/SOURCES.txt
pytry.egg-info/dependency_links.txt
pytry.egg-info/entry_points.txt
pytry.egg-info/top_level.txt