Metadata-Version: 1.1
Name: pytry
Version: 0.9.2
Summary: Running trials with parameter variation
Home-page: https://github.com/tcstewar/pytry
Author: Terry Stewart
Author-email: terry.stewart@gmail.com
License: GPLv3
Platform: UNKNOWN
Classifier: Development Status :: 4 - Beta
Classifier: Intended Audience :: Science/Research
Classifier: License :: OSI Approved :: GNU General Public License v3 (GPLv3)
Classifier: Programming Language :: Python :: 2
Classifier: Programming Language :: Python :: 3
Classifier: Topic :: Scientific/Engineering
